{
    "@class": "com.kony.gen.viz.model.container.KVizForm",
    "DNDConfig": null,
    "_margin_": [
        0,
        0,
        0,
        0
    ],
    "_orientation_": 1,
    "_padding_": [
        0,
        0,
        0,
        0
    ],
    "_percent_": true,
    "_skin_": "sc9f1e8e0fe241d7872a18a9f32b17c5",
    "_title_": null,
    "addWidgetsdone": false,
    "allboxes": [],
    "canUpdateUI": true,
    "children": [
        "RibbonsAnimation"
    ],
    "containerweight": 100,
    "currentLocale": "default",
    "device": "iPhoneXS",
    "displayorientation": 3,
    "enabledforidletimeout": false,
    "globalUserWidgetRefs": [
        "u0738f00f24349d9a1df3aa3e45065cb"
    ],
    "id": "userwidgetmodel",
    "info": null,
    "initdone": false,
    "inputaccessoryviewtype": 4,
    "intransitionconfig": {
        "formTransition": "None"
    },
    "iscustomlayout": false,
    "isvisible": true,
    "kuid": "u7836199a5ce4090b6f84a1fce99b8bd",
    "layouttype": 2,
    "masterType": 1,
    "name": "kony.ui.Form2",
    "needappmenu": true,
    "outtransitionconfig": {
        "formTransition": "None"
    },
    "paddinginpixel": false,
    "platform": "iphone",
    "prevDevice": "iPhoneXS",
    "prevPlatform": "iphone",
    "retaincontentalignment": false,
    "retainflexpositionproperties": false,
    "retainscrollposition": false,
    "shellCSS": "iOS_iPhoneXS",
    "titlebar": true,
    "type": 3,
    "wType": "Form"
}