{
    "classname": "notificationBubble",
    "definitions": {
        "apis": {
            "custom": [],
            "passthrough": []
        },
        "events": {
            "custom": [],
            "passthrough": []
        },
        "groups": {
            "apis": [],
            "events": [],
            "properties": [],
            "widgets": []
        },
        "properties": {
            "custom": [],
            "passthrough": [
                {
                    "access": "Enable",
                    "group": "General",
                    "kuid": "d6e34b530407450e8c30075aba9a2dd3",
                    "originalPropertyKey": "isVisible",
                    "propertyIndex": 1,
                    "propertyKey": "isVisible1",
                    "pw": {
                        "access": "readwrite",
                        "category": "look",
                        "dependentKeysKUIDs": null,
                        "displayName": "Notification Visibility",
                        "srcWidget": "containerFlex",
                        "type": "boolean",
                        "uiRepresentation": "Label-Radiobuttongroup",
                        "wType": "FlexContainer"
                    },
                    "srcWgtKUID": "a08df3a2ab9948eca35692031be02117"
                },
                {
                    "access": "Enable",
                    "group": "General",
                    "kuid": "cc9ea48d37f943519492630927a1738d",
                    "originalPropertyKey": "text",
                    "propertyIndex": 2,
                    "propertyKey": "notificationCount",
                    "pw": {
                        "access": "readwrite",
                        "category": "look",
                        "dependentKeysKUIDs": null,
                        "displayName": "Notification Count",
                        "srcWidget": "lblNotificationNumber",
                        "type": "string",
                        "uiRepresentation": "Label-Textbox",
                        "wType": "Label"
                    },
                    "srcWgtKUID": "g59309e4dd8a4578811d13ca03026410"
                }
            ]
        },
        "widgets": {
            "expose": [],
            "passthrough": []
        }
    },
    "namespace": "com.konyemea",
    "version": "1.0.0"
}